thumbnail_maker/__init__.py
thumbnail_maker/fields.py
thumbnail_maker/helpers.py
thumbnail_maker/models.py
thumbnail_maker/settings.py
thumbnail_maker/management/__init__.py
thumbnail_maker/management/commands/__init__.py
thumbnail_maker/management/commands/make_thumbnails.py
thumbnail_maker/templatetags/__init__.py
thumbnail_maker/templatetags/thumbnail_maker.py
django_thumbnail_maker-0.0.6.dist-info/LICENSE
django_thumbnail_maker-0.0.6.dist-info/METADATA
django_thumbnail_maker-0.0.6.dist-info/WHEEL
django_thumbnail_maker-0.0.6.dist-info/top_level.txt
django_thumbnail_maker-0.0.6.dist-info/RECORD
