Metadata-Version: 2.1
Name: django-thumbnail-maker
Version: 0.0.6
Summary: Thumbnail maker for Django
Home-page: https://github.com/infinityxxx/django-thumbnail-maker
Author: Tamara Khalbashkeeva
Author-email: infinityxxx@gmail.com
Maintainer: Tamara Khalbashkeeva
Maintainer-email: infinityxxx@gmail.com
License: BSD
Platform: any
Classifier: Environment :: Web Environment
Classifier: Framework :: Django
Classifier: Intended Audience :: Developers
Classifier: License :: OSI Approved :: BSD License
Classifier: Operating System :: OS Independent
Classifier: Programming Language :: Python
Classifier: Programming Language :: Python :: 2
Classifier: Programming Language :: Python :: 2.7
Classifier: Programming Language :: Python :: 3
Classifier: Programming Language :: Python :: 3.5
Classifier: Programming Language :: Python :: 3.6
Classifier: Programming Language :: Python :: 3.7
Classifier: Topic :: Internet :: WWW/HTTP :: Dynamic Content
Classifier: Topic :: Multimedia :: Graphics
Requires-Dist: sorl-thumbnail
